{
  "id": "36c81a07-c7fa-4bb4-a4d9-0569273029e1",
  "name": "APIM env template",
  "values": [
    {
      "key": "apim_consumer_private_key",
      "value": "put the value from nhc/apim-<env>-consumer-private-key secret from the account to which APIM proxy is connected ",
      "type": "default",
      "enabled": true
    },
    {
      "key": "apim_api_key",
      "value": "put the value from nhc/apim-<env>-consumer-api-key secret from the account to which APIM proxy is connected",
      "type": "default",
      "enabled": true
    },
    {
      "key": "apim_env_name",
      "value": "one of internal-dev/internal-qa/int",
      "type": "default",
      "enabled": true
    }
  ],
  "_postman_variable_scope": "environment",
  "_postman_exported_at": "2025-08-26T13:31:34.619Z",
  "_postman_exported_using": "Postman/11.58.0"
}
